{
    "size": 3,
    "board": "יעעמפמנוס",
    "words": [
        "מופע",
        "נמוס",
        "עמעמו",
        "מנומס",
        "נפעמו",
        "מיפו",
        "נופימ",
        "עפנו",
        "פונמי",
        "נוספימ",
        "מופעימ",
        "נפוס",
        "ספימ",
        "מעיפ",
        "ימנפ",
        "ימנפו",
        "פעמנו",
        "מומס",
        "מופס",
        "מופיע",
        "נפעמ",
        "סופי",
        "נוספ",
        "מסונפימ",
        "מופנמ",
        "פנמי",
        "נופעמ",
        "ימפו",
        "יפעמ",
        "ימונפ",
        "עפימ",
        "מנפי",
        "מנפו",
        "מעפנ",
        "נומי",
        "נופס",
        "מופעמ",
        "נופיע",
        "ספונ",
        "עמונ",
        "עמעמ",
        "פיעמ",
        "סמפונ",
        "ימנו",
        "מנוס",
        "מסונפ",
        "מונפ",
        "נומס",
        "יפעמו",
        "עמעמי",
        "מעמס",
        "מוספ",
        "פיעמנו",
        "פעמי",
        "עמנו",
        "יפוס",
        "עימומ",
        "סופימ",
        "מסופ",
        "מנופ",
        "נפעימ",
        "פעמונ",
        "מומנ",
        "יפנו",
        "יעמו",
        "מפעמ",
        "מפעימ",
        "נופי",
        "פעמו",
        "סומנ",
        "מוספימ",
        "עמוס",
        "מונפימ",
        "סונפ",
        "עמומ",
        "עמעמנו",
        "מסומנ",
        "פיעמו",
        "מסופימ"
    ],
    "wordsToLocations": {
        "יעמו": [
            [
                0,
                0
            ],
            [
                0,
                1
            ],
            [
                1,
                0
            ],
            [
                2,
                1
            ]
        ],
        "ימפו": [
            [
                0,
                0
            ],
            [
                1,
                0
            ],
            [
                1,
                1
            ],
            [
                2,
                1
            ]
        ],
        "ימנפ": [
            [
                0,
                0
            ],
            [
                1,
                0
            ],
            [
                2,
                0
            ],
            [
                1,
                1
            ]
        ],
        "ימנפו": [
            [
                0,
                0
            ],
            [
                1,
                0
            ],
            [
                2,
                0
            ],
            [
                1,
                1
            ],
            [
                2,
                1
            ]
        ],
        "ימנו": [
            [
                0,
                0
            ],
            [
                1,
                0
            ],
            [
                2,
                0
            ],
            [
                2,
                1
            ]
        ],
        "ימונפ": [
            [
                0,
                0
            ],
            [
                1,
                0
            ],
            [
                2,
                1
            ],
            [
                2,
                0
            ],
            [
                1,
                1
            ]
        ],
        "יפעמ": [
            [
                0,
                0
            ],
            [
                1,
                1
            ],
            [
                0,
                1
            ],
            [
                1,
                0
            ]
        ],
        "יפעמו": [
            [
                0,
                0
            ],
            [
                1,
                1
            ],
            [
                0,
                1
            ],
            [
                1,
                0
            ],
            [
                2,
                1
            ]
        ],
        "יפנו": [
            [
                0,
                0
            ],
            [
                1,
                1
            ],
            [
                2,
                0
            ],
            [
                2,
                1
            ]
        ],
        "יפוס": [
            [
                0,
                0
            ],
            [
                1,
                1
            ],
            [
                2,
                1
            ],
            [
                2,
                2
            ]
        ],
        "עימומ": [
            [
                0,
                1
            ],
            [
                0,
                0
            ],
            [
                1,
                0
            ],
            [
                2,
                1
            ],
            [
                1,
                2
            ]
        ],
        "עמנו": [
            [
                0,
                1
            ],
            [
                1,
                0
            ],
            [
                2,
                0
            ],
            [
                2,
                1
            ]
        ],
        "עמומ": [
            [
                0,
                1
            ],
            [
                1,
                0
            ],
            [
                2,
                1
            ],
            [
                1,
                2
            ]
        ],
        "עמונ": [
            [
                0,
                1
            ],
            [
                1,
                0
            ],
            [
                2,
                1
            ],
            [
                2,
                0
            ]
        ],
        "עמוס": [
            [
                0,
                1
            ],
            [
                1,
                0
            ],
            [
                2,
                1
            ],
            [
                2,
                2
            ]
        ],
        "עפימ": [
            [
                0,
                1
            ],
            [
                1,
                1
            ],
            [
                0,
                0
            ],
            [
                1,
                0
            ]
        ],
        "עפנו": [
            [
                0,
                1
            ],
            [
                1,
                1
            ],
            [
                2,
                0
            ],
            [
                2,
                1
            ]
        ],
        "עמעמ": [
            [
                0,
                2
            ],
            [
                1,
                2
            ],
            [
                0,
                1
            ],
            [
                1,
                0
            ]
        ],
        "עמעמי": [
            [
                0,
                2
            ],
            [
                1,
                2
            ],
            [
                0,
                1
            ],
            [
                1,
                0
            ],
            [
                0,
                0
            ]
        ],
        "עמעמנו": [
            [
                0,
                2
            ],
            [
                1,
                2
            ],
            [
                0,
                1
            ],
            [
                1,
                0
            ],
            [
                2,
                0
            ],
            [
                2,
                1
            ]
        ],
        "עמעמו": [
            [
                0,
                2
            ],
            [
                1,
                2
            ],
            [
                0,
                1
            ],
            [
                1,
                0
            ],
            [
                2,
                1
            ]
        ],
        "מיפו": [
            [
                1,
                0
            ],
            [
                0,
                0
            ],
            [
                1,
                1
            ],
            [
                2,
                1
            ]
        ],
        "מעיפ": [
            [
                1,
                0
            ],
            [
                0,
                1
            ],
            [
                0,
                0
            ],
            [
                1,
                1
            ]
        ],
        "מעפנ": [
            [
                1,
                0
            ],
            [
                0,
                1
            ],
            [
                1,
                1
            ],
            [
                2,
                0
            ]
        ],
        "מעמס": [
            [
                1,
                0
            ],
            [
                0,
                1
            ],
            [
                1,
                2
            ],
            [
                2,
                2
            ]
        ],
        "מפעמ": [
            [
                1,
                0
            ],
            [
                1,
                1
            ],
            [
                0,
                1
            ],
            [
                1,
                2
            ]
        ],
        "מנפי": [
            [
                1,
                0
            ],
            [
                2,
                0
            ],
            [
                1,
                1
            ],
            [
                0,
                0
            ]
        ],
        "מנפו": [
            [
                1,
                0
            ],
            [
                2,
                0
            ],
            [
                1,
                1
            ],
            [
                2,
                1
            ]
        ],
        "מנופ": [
            [
                1,
                0
            ],
            [
                2,
                0
            ],
            [
                2,
                1
            ],
            [
                1,
                1
            ]
        ],
        "מנומס": [
            [
                1,
                0
            ],
            [
                2,
                0
            ],
            [
                2,
                1
            ],
            [
                1,
                2
            ],
            [
                2,
                2
            ]
        ],
        "מנוס": [
            [
                1,
                0
            ],
            [
                2,
                0
            ],
            [
                2,
                1
            ],
            [
                2,
                2
            ]
        ],
        "מופיע": [
            [
                1,
                0
            ],
            [
                2,
                1
            ],
            [
                1,
                1
            ],
            [
                0,
                0
            ],
            [
                0,
                1
            ]
        ],
        "מופע": [
            [
                1,
                0
            ],
            [
                2,
                1
            ],
            [
                1,
                1
            ],
            [
                0,
                1
            ]
        ],
        "מופעמ": [
            [
                1,
                0
            ],
            [
                2,
                1
            ],
            [
                1,
                1
            ],
            [
                0,
                1
            ],
            [
                1,
                2
            ]
        ],
        "מופס": [
            [
                1,
                0
            ],
            [
                2,
                1
            ],
            [
                1,
                1
            ],
            [
                2,
                2
            ]
        ],
        "מומס": [
            [
                1,
                0
            ],
            [
                2,
                1
            ],
            [
                1,
                2
            ],
            [
                2,
                2
            ]
        ],
        "מונפ": [
            [
                1,
                0
            ],
            [
                2,
                1
            ],
            [
                2,
                0
            ],
            [
                1,
                1
            ]
        ],
        "מוספ": [
            [
                1,
                0
            ],
            [
                2,
                1
            ],
            [
                2,
                2
            ],
            [
                1,
                1
            ]
        ],
        "פיעמ": [
            [
                1,
                1
            ],
            [
                0,
                0
            ],
            [
                0,
                1
            ],
            [
                1,
                0
            ]
        ],
        "פיעמנו": [
            [
                1,
                1
            ],
            [
                0,
                0
            ],
            [
                0,
                1
            ],
            [
                1,
                0
            ],
            [
                2,
                0
            ],
            [
                2,
                1
            ]
        ],
        "פיעמו": [
            [
                1,
                1
            ],
            [
                0,
                0
            ],
            [
                0,
                1
            ],
            [
                1,
                0
            ],
            [
                2,
                1
            ]
        ],
        "פעמי": [
            [
                1,
                1
            ],
            [
                0,
                1
            ],
            [
                1,
                0
            ],
            [
                0,
                0
            ]
        ],
        "פעמנו": [
            [
                1,
                1
            ],
            [
                0,
                1
            ],
            [
                1,
                0
            ],
            [
                2,
                0
            ],
            [
                2,
                1
            ]
        ],
        "פעמו": [
            [
                1,
                1
            ],
            [
                0,
                1
            ],
            [
                1,
                0
            ],
            [
                2,
                1
            ]
        ],
        "פעמונ": [
            [
                1,
                1
            ],
            [
                0,
                1
            ],
            [
                1,
                0
            ],
            [
                2,
                1
            ],
            [
                2,
                0
            ]
        ],
        "פנמי": [
            [
                1,
                1
            ],
            [
                2,
                0
            ],
            [
                1,
                0
            ],
            [
                0,
                0
            ]
        ],
        "פונמי": [
            [
                1,
                1
            ],
            [
                2,
                1
            ],
            [
                2,
                0
            ],
            [
                1,
                0
            ],
            [
                0,
                0
            ]
        ],
        "מפעימ": [
            [
                1,
                2
            ],
            [
                1,
                1
            ],
            [
                0,
                1
            ],
            [
                0,
                0
            ],
            [
                1,
                0
            ]
        ],
        "מומנ": [
            [
                1,
                2
            ],
            [
                2,
                1
            ],
            [
                1,
                0
            ],
            [
                2,
                0
            ]
        ],
        "מופעימ": [
            [
                1,
                2
            ],
            [
                2,
                1
            ],
            [
                1,
                1
            ],
            [
                0,
                1
            ],
            [
                0,
                0
            ],
            [
                1,
                0
            ]
        ],
        "מופנמ": [
            [
                1,
                2
            ],
            [
                2,
                1
            ],
            [
                1,
                1
            ],
            [
                2,
                0
            ],
            [
                1,
                0
            ]
        ],
        "מונפימ": [
            [
                1,
                2
            ],
            [
                2,
                1
            ],
            [
                2,
                0
            ],
            [
                1,
                1
            ],
            [
                0,
                0
            ],
            [
                1,
                0
            ]
        ],
        "מוספימ": [
            [
                1,
                2
            ],
            [
                2,
                1
            ],
            [
                2,
                2
            ],
            [
                1,
                1
            ],
            [
                0,
                0
            ],
            [
                1,
                0
            ]
        ],
        "מסומנ": [
            [
                1,
                2
            ],
            [
                2,
                2
            ],
            [
                2,
                1
            ],
            [
                1,
                0
            ],
            [
                2,
                0
            ]
        ],
        "מסופ": [
            [
                1,
                2
            ],
            [
                2,
                2
            ],
            [
                2,
                1
            ],
            [
                1,
                1
            ]
        ],
        "מסופימ": [
            [
                1,
                2
            ],
            [
                2,
                2
            ],
            [
                2,
                1
            ],
            [
                1,
                1
            ],
            [
                0,
                0
            ],
            [
                1,
                0
            ]
        ],
        "מסונפ": [
            [
                1,
                2
            ],
            [
                2,
                2
            ],
            [
                2,
                1
            ],
            [
                2,
                0
            ],
            [
                1,
                1
            ]
        ],
        "מסונפימ": [
            [
                1,
                2
            ],
            [
                2,
                2
            ],
            [
                2,
                1
            ],
            [
                2,
                0
            ],
            [
                1,
                1
            ],
            [
                0,
                0
            ],
            [
                1,
                0
            ]
        ],
        "נמוס": [
            [
                2,
                0
            ],
            [
                1,
                0
            ],
            [
                2,
                1
            ],
            [
                2,
                2
            ]
        ],
        "נפעימ": [
            [
                2,
                0
            ],
            [
                1,
                1
            ],
            [
                0,
                1
            ],
            [
                0,
                0
            ],
            [
                1,
                0
            ]
        ],
        "נפעמ": [
            [
                2,
                0
            ],
            [
                1,
                1
            ],
            [
                0,
                1
            ],
            [
                1,
                0
            ]
        ],
        "נפעמו": [
            [
                2,
                0
            ],
            [
                1,
                1
            ],
            [
                0,
                1
            ],
            [
                1,
                0
            ],
            [
                2,
                1
            ]
        ],
        "נפוס": [
            [
                2,
                0
            ],
            [
                1,
                1
            ],
            [
                2,
                1
            ],
            [
                2,
                2
            ]
        ],
        "נומי": [
            [
                2,
                0
            ],
            [
                2,
                1
            ],
            [
                1,
                0
            ],
            [
                0,
                0
            ]
        ],
        "נופי": [
            [
                2,
                0
            ],
            [
                2,
                1
            ],
            [
                1,
                1
            ],
            [
                0,
                0
            ]
        ],
        "נופיע": [
            [
                2,
                0
            ],
            [
                2,
                1
            ],
            [
                1,
                1
            ],
            [
                0,
                0
            ],
            [
                0,
                1
            ]
        ],
        "נופימ": [
            [
                2,
                0
            ],
            [
                2,
                1
            ],
            [
                1,
                1
            ],
            [
                0,
                0
            ],
            [
                1,
                0
            ]
        ],
        "נופעמ": [
            [
                2,
                0
            ],
            [
                2,
                1
            ],
            [
                1,
                1
            ],
            [
                0,
                1
            ],
            [
                1,
                0
            ]
        ],
        "נופס": [
            [
                2,
                0
            ],
            [
                2,
                1
            ],
            [
                1,
                1
            ],
            [
                2,
                2
            ]
        ],
        "נומס": [
            [
                2,
                0
            ],
            [
                2,
                1
            ],
            [
                1,
                2
            ],
            [
                2,
                2
            ]
        ],
        "נוספ": [
            [
                2,
                0
            ],
            [
                2,
                1
            ],
            [
                2,
                2
            ],
            [
                1,
                1
            ]
        ],
        "נוספימ": [
            [
                2,
                0
            ],
            [
                2,
                1
            ],
            [
                2,
                2
            ],
            [
                1,
                1
            ],
            [
                0,
                0
            ],
            [
                1,
                0
            ]
        ],
        "ספימ": [
            [
                2,
                2
            ],
            [
                1,
                1
            ],
            [
                0,
                0
            ],
            [
                1,
                0
            ]
        ],
        "ספונ": [
            [
                2,
                2
            ],
            [
                1,
                1
            ],
            [
                2,
                1
            ],
            [
                2,
                0
            ]
        ],
        "סמפונ": [
            [
                2,
                2
            ],
            [
                1,
                2
            ],
            [
                1,
                1
            ],
            [
                2,
                1
            ],
            [
                2,
                0
            ]
        ],
        "סומנ": [
            [
                2,
                2
            ],
            [
                2,
                1
            ],
            [
                1,
                0
            ],
            [
                2,
                0
            ]
        ],
        "סופי": [
            [
                2,
                2
            ],
            [
                2,
                1
            ],
            [
                1,
                1
            ],
            [
                0,
                0
            ]
        ],
        "סופימ": [
            [
                2,
                2
            ],
            [
                2,
                1
            ],
            [
                1,
                1
            ],
            [
                0,
                0
            ],
            [
                1,
                0
            ]
        ],
        "סונפ": [
            [
                2,
                2
            ],
            [
                2,
                1
            ],
            [
                2,
                0
            ],
            [
                1,
                1
            ]
        ]
    },
    "cellStartingWordCounts": [
        10,
        7,
        4,
        17,
        9,
        11,
        14,
        0,
        7
    ],
    "cellPassingWordCounts": [
        38,
        35,
        4,
        64,
        58,
        24,
        45,
        62,
        27
    ]
}